django_flexquery/__init__.py
django_flexquery/flexquery.py
django_flexquery/q.py
django_flexquery/contrib/__init__.py
django_flexquery/contrib/user_based.py
django_flexquery-4.2.0.dist-info/METADATA
django_flexquery-4.2.0.dist-info/WHEEL
django_flexquery-4.2.0.dist-info/top_level.txt
django_flexquery-4.2.0.dist-info/RECORD
