Metadata-Version: 2.1
Name: django-flexquery
Version: 4.2.0
Summary: Reusable QuerySet filtering logic for Django, incorporating the DRY principle and maximizing user experience and performance
Home-page: https://github.com/efficiosoft/django-flexquery
Author: Robert Schindler
Author-email: r.schindler@efficiosoft.com
License: MIT License
Platform: UNKNOWN
Requires-Dist: django (<3.1,>=2.2)
